ctgu_sql_query_tool/__init__.py
ctgu_sql_query_tool-0.1.0.dist-info/WHEEL
ctgu_sql_query_tool-0.1.0.dist-info/entry_points.txt
ctgu_sql_query_tool-0.1.0.dist-info/METADATA
ctgu_sql_query_tool-0.1.0.dist-info/RECORD
