Metadata-Version: 2.3
Name: ctgu-sql-query-tool
Version: 0.1.0
Summary: Add your description here
Author: 郭晓阳
Author-email: 郭晓阳 <guoxiaoyang@ctgu.edu.cn>
Requires-Dist: langchain-core>=1.2.6
Requires-Dist: loguru>=0.7.3
Requires-Dist: mcp[cli]>=1.25.0
Requires-Dist: psycopg2>=2.9.11
Requires-Dist: pymysql>=1.1.2
Requires-Dist: sqlalchemy>=2.0.45
Requires-Python: >=3.13
